{
    "team": [
        {
            "name": "Chamodi Dikela",
            "email": "e21096@eng.pdn.ac.lk",
            "eNumber": "E/21/096"
        },
        {
            "name": "Navoda Erandi",
            "email": "e21127@eng.pdn.ac.lk",
            "eNumber": "E/21/127"
        },
        {
            "name": "Suvini Fonseka",
            "email": "e21140@eng.pdn.ac.lk",
            "eNumber": "E/21/140"
        },
        {
            "name": "Tharushi Savindi",
            "email": "e21363@eng.pdn.ac.lk",
            "eNumber": "E/21/363"
        }
    ],
    "supervisors": [
        {
            "name": "Ms. Yasodha Vimukthi",
            "email": "yasodhav@eng.pdn.ac.lk"
        }
        
    ],
    "tags": ["Web", "Embedded Systems"]
}
